tmux_popup/__init__.py
tmux_popup/canvas.py
tmux_popup/content.py
tmux_popup/core/__init__.py
tmux_popup/core/base.py
tmux_popup/core/builder.py
tmux_popup/core/types.py
tmux_popup/core/utils.py
tmux_popup/interactive/__init__.py
tmux_popup/interactive/choose.py
tmux_popup/interactive/confirm.py
tmux_popup/interactive/file.py
tmux_popup/interactive/filter.py
tmux_popup/interactive/format.py
tmux_popup/interactive/input.py
tmux_popup/interactive/pager.py
tmux_popup/interactive/spin.py
tmux_popup/interactive/table.py
tmux_popup/layout.py
tmux_popup/popup.py
tmux_popup-0.2.2.dist-info/WHEEL
tmux_popup-0.2.2.dist-info/METADATA
tmux_popup-0.2.2.dist-info/RECORD
