Metadata-Version: 2.3
Name: tmux-popup
Version: 0.2.2
Summary: Composable tmux popup system with gum UI components
Keywords: tmux,terminal,popup,gum,tui,cli
Author: Fredrik Angelsen
Author-email: Fredrik Angelsen <fredrikangelsen@gmail.com>
License: MIT
Classifier: Development Status :: 4 - Beta
Classifier: Intended Audience :: Developers
Classifier: License :: OSI Approved :: MIT License
Classifier: Programming Language :: Python :: 3.12
Classifier: Topic :: Terminals
Requires-Dist: flask>=3.1.1 ; extra == 'examples'
Requires-Python: >=3.12
Project-URL: Issues, https://github.com/angelsen/tap-tools/issues
Project-URL: Repository, https://github.com/angelsen/tap-tools
Provides-Extra: examples
